sadales_tikls_m2m_api_client/__init__.py
sadales_tikls_m2m_api_client/api/__init__.py
sadales_tikls_m2m_api_client/api/default/__init__.py
sadales_tikls_m2m_api_client/api/default/get_object_consumption.py
sadales_tikls_m2m_api_client/api/default/get_object_list.py
sadales_tikls_m2m_api_client/client.py
sadales_tikls_m2m_api_client/models/__init__.py
sadales_tikls_m2m_api_client/models/error.py
sadales_tikls_m2m_api_client/models/error_invalid_params_item.py
sadales_tikls_m2m_api_client/models/get_object_consumption_response_200_item.py
sadales_tikls_m2m_api_client/models/get_object_consumption_response_200_item_m_list_item.py
sadales_tikls_m2m_api_client/models/get_object_consumption_response_200_item_m_list_item_c_list_item.py
sadales_tikls_m2m_api_client/models/get_object_consumption_response_200_item_m_list_item_c_list_item_cvr_st.py
sadales_tikls_m2m_api_client/models/get_object_list_response_200.py
sadales_tikls_m2m_api_client/models/get_object_list_response_200o_list_item.py
sadales_tikls_m2m_api_client/models/get_object_list_response_200o_list_item_mp_list_item.py
sadales_tikls_m2m_api_client/models/get_object_list_response_200o_list_item_mp_list_item_m_list_item.py
sadales_tikls_m2m_api_client/models/get_object_list_response_200o_list_item_o_addr.py
sadales_tikls_m2m_api_client/py.typed
sadales_tikls_m2m_api_client/types.py
sadales_tikls_m2m-1.0.0.dist-info/WHEEL
sadales_tikls_m2m-1.0.0.dist-info/METADATA
sadales_tikls_m2m-1.0.0.dist-info/RECORD
