Metadata-Version: 2.1
Name: sadales-tikls-m2m
Version: 1.0.0
Summary: A client library for accessing Sadales Tikls M2M API
Home-page: https://github.com/vermut/sadales-tikls-m2m
License: Apache 2.0
Author: Pavels Veretennikovs
Author-email: vermut@pm.me
Requires-Python: >=3.6,<4.0
Classifier: License :: Other/Proprietary License
Classifier: Programming Language :: Python :: 3
Classifier: Programming Language :: Python :: 3.10
Classifier: Programming Language :: Python :: 3.6
Classifier: Programming Language :: Python :: 3.7
Classifier: Programming Language :: Python :: 3.8
Classifier: Programming Language :: Python :: 3.9
Requires-Dist: attrs (>=20.1.0,<22.0.0)
Requires-Dist: httpx (>=0.15.4,<0.20.0)
Requires-Dist: python-dateutil (>=2.8.0,<3.0.0)
Project-URL: Repository, https://github.com/vermut/sadales-tikls-m2m
